flatmed/__init__.py
flatmed/flatmed.py
flatmed-0.0.1.dist-info/LICENSE.txt
flatmed-0.0.1.dist-info/METADATA
flatmed-0.0.1.dist-info/WHEEL
flatmed-0.0.1.dist-info/top_level.txt
flatmed-0.0.1.dist-info/RECORD
