Metadata-Version: 2.1
Name: flatmed
Version: 0.0.1
Summary: A simple package for converting PubMed output (ie, the output from PubMed with all PubMed fields) into a flat file or pandas.DataFrame object. Simple functions are provided to merge the results of separate searches and automatically create variables indicating which search(es) a record was found in. Users can then add their own notes on the references by importing the flat file into a spreadsheet program of their choice and adding their notes in new columns.
Author-email: Ray Griner <rgriner_fwd@outlook.com>
License: GNU GENERAL PUBLIC LICENSE
Keywords: PubMed,parser
Classifier: Programming Language :: Python :: 3
Classifier: License :: OSI Approved :: GNU General Public License v3 or later (GPLv3+)
Classifier: Operating System :: OS Independent
Classifier: Development Status :: 3 - Alpha
Classifier: Intended Audience :: Healthcare Industry
License-File: LICENSE.txt
